microfilter/__init__.py
microfilter/univariate/__init__.py
microfilter/univariate/digestdist.py
microfilter/univariate/distmachine.py
microfilter/univariate/expnormdist.py
microfilter/univariate/fitdist.py
microfilter/univariate/noisysim.py
microfilter/univariate/normaldist.py
microfilter/univariate/runningmoments.py
microfilter/univariate/skewdist.py
microfilter-0.0.9.dist-info/METADATA
microfilter-0.0.9.dist-info/WHEEL
microfilter-0.0.9.dist-info/entry_points.txt
microfilter-0.0.9.dist-info/top_level.txt
microfilter-0.0.9.dist-info/RECORD
