Metadata-Version: 2.1
Name: microfilter
Version: 0.0.9
Summary: Filtering noisy data
Home-page: https://github.com/microprediction/microfilter
Author: microprediction
Author-email: pcotton@intechinvestments.com
License: MIT
Platform: UNKNOWN
Classifier: License :: OSI Approved :: MIT License
Classifier: Programming Language :: Python :: 3
Classifier: Programming Language :: Python :: 3.7
Requires-Dist: pandas
Requires-Dist: numpy
Requires-Dist: pytest
Requires-Dist: statsmodels
Requires-Dist: hyperopt
Requires-Dist: scipy
Requires-Dist: matplotlib
Requires-Dist: microconventions (<0.4)
Requires-Dist: wheel
